{
  "$schema": "https://dev.office.com/json-schemas/spfx-build/package-solution.schema.json",
  "solution": {
    "name": "pnpjs-spfx-1-4-1-appcustheader-client-side-solution",
    "id": "5d6838f1-db79-4045-89ca-7772779f0054",
    "version": "1.0.0.0",
    "includeClientSideAssets": true,
    "features": [
      {
        "title": "Application Extension - Deployment of custom action.",
        "description": "Deploys a custom action with ClientSideComponentId association",
        "id": "a0d858d4-5696-4847-8254-5ce393c4787c",
        "version": "1.0.0.0",
        "assets": {
          "elementManifests": [
            "elements.xml"
          ]
        }
      }
    ]
  },
  "paths": {
    "zippedPackage": "solution/pnpjs-spfx-1-4-1-appcustheader.sppkg"
  }
}
